{
    "meta": {
        "id": 1418888,
        "name": "Ferenc Sípos",
        "team": "Hungary",
        "year": "1966",
        "season_id": 17564,
        "position": "D"
    },
    "stats": {
        "rating": 7.175,
        "totalRating": 28.7,
        "countRating": 4,
        "goals": 0,
        "bigChancesCreated": 0,
        "bigChancesMissed": 0,
        "assists": 1,
        "goalsAssistsSum": 1,
        "accuratePasses": 143,
        "inaccuratePasses": 40,
        "totalPasses": 183,
        "accuratePassesPercentage": 78.142076502732,
        "accurateOwnHalfPasses": 57,
        "accurateOppositionHalfPasses": 86,
        "accurateFinalThirdPasses": 43,
        "keyPasses": 5,
        "successfulDribbles": 3,
        "successfulDribblesPercentage": 75,
        "tackles": 16,
        "interceptions": 12,
        "yellowCards": 0,
        "directRedCards": 0,
        "redCards": 0,
        "accurateCrosses": 0,
        "accurateCrossesPercentage": 0,
        "totalShots": 5,
        "shotsOnTarget": 3,
        "shotsOffTarget": 1,
        "groundDuelsWon": 20,
        "groundDuelsWonPercentage": 52.631578947368,
        "aerialDuelsWon": 2,
        "aerialDuelsWonPercentage": 50,
        "totalDuelsWon": 22,
        "totalDuelsWonPercentage": 52.380952380952,
        "minutesPlayed": 360,
        "goalConversionPercentage": 0,
        "penaltiesTaken": 0,
        "penaltyGoals": 0,
        "penaltyWon": 0,
        "penaltyConceded": 0,
        "shotFromSetPiece": 1,
        "freeKickGoal": 0,
        "goalsFromInsideTheBox": 0,
        "goalsFromOutsideTheBox": 0,
        "shotsFromInsideTheBox": 1,
        "shotsFromOutsideTheBox": 4,
        "headedGoals": 0,
        "leftFootGoals": 0,
        "rightFootGoals": 0,
        "accurateLongBalls": 14,
        "accurateLongBallsPercentage": 73.684210526316,
        "clearances": 9,
        "errorLeadToGoal": 0,
        "errorLeadToShot": 0,
        "dispossessed": 3,
        "possessionLost": 44,
        "possessionWonAttThird": 0,
        "totalChippedPasses": 14,
        "accurateChippedPasses": 10,
        "touches": 240,
        "wasFouled": 1,
        "fouls": 4,
        "hitWoodwork": 0,
        "ownGoals": 0,
        "dribbledPast": 10,
        "offsides": 0,
        "blockedShots": 1,
        "passToAssist": 0,
        "saves": 0,
        "cleanSheet": 0,
        "penaltyFaced": 0,
        "penaltySave": 0,
        "savedShotsFromInsideTheBox": 0,
        "savedShotsFromOutsideTheBox": 0,
        "goalsConcededInsideTheBox": 7,
        "goalsConcededOutsideTheBox": 0,
        "punches": 0,
        "runsOut": 0,
        "successfulRunsOut": 0,
        "highClaims": 0,
        "crossesNotClaimed": 0,
        "matchesStarted": 4,
        "penaltyConversion": 0,
        "setPieceConversion": 0,
        "totalAttemptAssist": 5,
        "totalContest": 4,
        "totalCross": 0,
        "duelLost": 20,
        "aerialLost": 2,
        "attemptPenaltyMiss": 0,
        "attemptPenaltyPost": 0,
        "attemptPenaltyTarget": 0,
        "totalLongBalls": 19,
        "goalsConceded": 7,
        "tacklesWon": 10,
        "tacklesWonPercentage": 62.5,
        "scoringFrequency": 0,
        "yellowRedCards": 0,
        "savesCaught": 0,
        "savesParried": 0,
        "totalOwnHalfPasses": 67,
        "totalOppositionHalfPasses": 116,
        "totwAppearances": 0,
        "id": 903451,
        "type": "overall",
        "appearances": 4,
        "statisticsType": {
            "sportSlug": "football",
            "statisticsType": "player"
        }
    }
}