{
    "meta": {
        "id": 260,
        "name": "Carsten Ramelow",
        "team": "Germany",
        "year": "2002",
        "season_id": 2636,
        "position": "M"
    },
    "stats": {
        "rating": 6.82,
        "totalRating": 34.1,
        "countRating": 5,
        "goals": 0,
        "bigChancesCreated": 0,
        "bigChancesMissed": 0,
        "assists": 0,
        "goalsAssistsSum": 0,
        "accuratePasses": 169,
        "inaccuratePasses": 26,
        "totalPasses": 195,
        "accuratePassesPercentage": 86.666666666667,
        "accurateOwnHalfPasses": 118,
        "accurateOppositionHalfPasses": 51,
        "accurateFinalThirdPasses": 22,
        "keyPasses": 2,
        "successfulDribbles": 1,
        "successfulDribblesPercentage": 50,
        "tackles": 9,
        "interceptions": 9,
        "yellowCards": 0,
        "directRedCards": 0,
        "redCards": 1,
        "accurateCrosses": 0,
        "accurateCrossesPercentage": 0,
        "totalShots": 3,
        "shotsOnTarget": 1,
        "shotsOffTarget": 0,
        "groundDuelsWon": 16,
        "groundDuelsWonPercentage": 57.142857142857,
        "aerialDuelsWon": 5,
        "aerialDuelsWonPercentage": 83.333333333333,
        "totalDuelsWon": 21,
        "totalDuelsWonPercentage": 61.764705882353,
        "minutesPlayed": 355,
        "goalConversionPercentage": 0,
        "penaltiesTaken": 0,
        "penaltyGoals": 0,
        "penaltyWon": 0,
        "penaltyConceded": 0,
        "shotFromSetPiece": 0,
        "freeKickGoal": 0,
        "goalsFromInsideTheBox": 0,
        "goalsFromOutsideTheBox": 0,
        "shotsFromInsideTheBox": 1,
        "shotsFromOutsideTheBox": 2,
        "headedGoals": 0,
        "leftFootGoals": 0,
        "rightFootGoals": 0,
        "accurateLongBalls": 18,
        "accurateLongBallsPercentage": 72,
        "clearances": 19,
        "errorLeadToGoal": 0,
        "errorLeadToShot": 0,
        "dispossessed": 2,
        "possessionLost": 32,
        "possessionWonAttThird": 0,
        "totalChippedPasses": 18,
        "accurateChippedPasses": 10,
        "touches": 254,
        "wasFouled": 6,
        "fouls": 6,
        "hitWoodwork": 0,
        "ownGoals": 0,
        "dribbledPast": 3,
        "offsides": 0,
        "blockedShots": 2,
        "passToAssist": 0,
        "saves": 0,
        "cleanSheet": 1,
        "penaltyFaced": 0,
        "penaltySave": 0,
        "savedShotsFromInsideTheBox": 0,
        "savedShotsFromOutsideTheBox": 0,
        "goalsConcededInsideTheBox": 3,
        "goalsConcededOutsideTheBox": 0,
        "punches": 0,
        "runsOut": 0,
        "successfulRunsOut": 0,
        "highClaims": 0,
        "crossesNotClaimed": 0,
        "matchesStarted": 5,
        "penaltyConversion": 0,
        "setPieceConversion": 0,
        "totalAttemptAssist": 2,
        "totalContest": 2,
        "totalCross": 2,
        "duelLost": 13,
        "aerialLost": 1,
        "attemptPenaltyMiss": 0,
        "attemptPenaltyPost": 0,
        "attemptPenaltyTarget": 0,
        "totalLongBalls": 25,
        "goalsConceded": 3,
        "tacklesWon": 9,
        "tacklesWonPercentage": 100,
        "scoringFrequency": 0,
        "yellowRedCards": 1,
        "savesCaught": 0,
        "savesParried": 0,
        "totalOwnHalfPasses": 121,
        "totalOppositionHalfPasses": 76,
        "totwAppearances": 0,
        "id": 911836,
        "type": "overall",
        "appearances": 5,
        "statisticsType": {
            "sportSlug": "football",
            "statisticsType": "player"
        }
    }
}