{
    "meta": {
        "id": 1422825,
        "name": "Noel Valladares",
        "team": "Honduras",
        "year": "2010",
        "season_id": 2531,
        "position": "G"
    },
    "stats": {
        "rating": 7.1333333333333,
        "totalRating": 21.4,
        "countRating": 3,
        "goals": 0,
        "bigChancesCreated": 0,
        "bigChancesMissed": 0,
        "assists": 0,
        "goalsAssistsSum": 0,
        "accuratePasses": 48,
        "inaccuratePasses": 45,
        "totalPasses": 93,
        "accuratePassesPercentage": 51.612903225806,
        "accurateOwnHalfPasses": 32,
        "accurateOppositionHalfPasses": 16,
        "accurateFinalThirdPasses": 5,
        "keyPasses": 0,
        "successfulDribbles": 0,
        "successfulDribblesPercentage": 0,
        "tackles": 0,
        "interceptions": 1,
        "yellowCards": 0,
        "directRedCards": 0,
        "redCards": 0,
        "accurateCrosses": 0,
        "accurateCrossesPercentage": 0,
        "totalShots": 0,
        "shotsOnTarget": 0,
        "shotsOffTarget": 0,
        "groundDuelsWon": 0,
        "groundDuelsWonPercentage": 0,
        "aerialDuelsWon": 0,
        "aerialDuelsWonPercentage": 0,
        "totalDuelsWon": 0,
        "totalDuelsWonPercentage": 0,
        "minutesPlayed": 270,
        "goalConversionPercentage": 0,
        "penaltiesTaken": 0,
        "penaltyGoals": 0,
        "penaltyWon": 0,
        "penaltyConceded": 0,
        "shotFromSetPiece": 0,
        "freeKickGoal": 0,
        "goalsFromInsideTheBox": 0,
        "goalsFromOutsideTheBox": 0,
        "shotsFromInsideTheBox": 0,
        "shotsFromOutsideTheBox": 0,
        "headedGoals": 0,
        "leftFootGoals": 0,
        "rightFootGoals": 0,
        "accurateLongBalls": 20,
        "accurateLongBallsPercentage": 32.786885245902,
        "clearances": 5,
        "errorLeadToGoal": 0,
        "errorLeadToShot": 0,
        "dispossessed": 0,
        "possessionLost": 46,
        "possessionWonAttThird": 0,
        "totalChippedPasses": 1,
        "accurateChippedPasses": 0,
        "touches": 124,
        "wasFouled": 0,
        "fouls": 0,
        "hitWoodwork": 0,
        "ownGoals": 0,
        "dribbledPast": 0,
        "offsides": 0,
        "blockedShots": 0,
        "passToAssist": 0,
        "saves": 12,
        "cleanSheet": 1,
        "penaltyFaced": 1,
        "penaltySave": 0,
        "savedShotsFromInsideTheBox": 8,
        "savedShotsFromOutsideTheBox": 4,
        "goalsConcededInsideTheBox": 2,
        "goalsConcededOutsideTheBox": 1,
        "punches": 4,
        "runsOut": 0,
        "successfulRunsOut": 0,
        "highClaims": 3,
        "crossesNotClaimed": 0,
        "matchesStarted": 3,
        "penaltyConversion": 0,
        "setPieceConversion": 0,
        "totalAttemptAssist": 0,
        "totalContest": 0,
        "totalCross": 0,
        "duelLost": 0,
        "aerialLost": 0,
        "attemptPenaltyMiss": 0,
        "attemptPenaltyPost": 0,
        "attemptPenaltyTarget": 0,
        "totalLongBalls": 61,
        "goalsConceded": 3,
        "tacklesWon": 0,
        "tacklesWonPercentage": 0,
        "scoringFrequency": 0,
        "yellowRedCards": 0,
        "savesCaught": 1,
        "savesParried": 0,
        "totalOwnHalfPasses": 39,
        "totalOppositionHalfPasses": 54,
        "totwAppearances": 0,
        "id": 916328,
        "type": "overall",
        "appearances": 3,
        "statisticsType": {
            "sportSlug": "football",
            "statisticsType": "player"
        }
    }
}