{
    "meta": {
        "id": 176139,
        "name": "Edison Flores",
        "team": "Peru",
        "year": "2018",
        "season_id": 15586,
        "position": "F"
    },
    "stats": {
        "rating": 6.6333333333333,
        "totalRating": 19.9,
        "countRating": 3,
        "goals": 0,
        "bigChancesCreated": 0,
        "bigChancesMissed": 0,
        "assists": 0,
        "goalsAssistsSum": 0,
        "accuratePasses": 77,
        "inaccuratePasses": 23,
        "totalPasses": 100,
        "accuratePassesPercentage": 77,
        "accurateOwnHalfPasses": 28,
        "accurateOppositionHalfPasses": 50,
        "accurateFinalThirdPasses": 29,
        "keyPasses": 2,
        "successfulDribbles": 2,
        "successfulDribblesPercentage": 66.666666666667,
        "tackles": 5,
        "interceptions": 2,
        "yellowCards": 0,
        "directRedCards": 0,
        "redCards": 0,
        "accurateCrosses": 1,
        "accurateCrossesPercentage": 50,
        "totalShots": 4,
        "shotsOnTarget": 1,
        "shotsOffTarget": 2,
        "groundDuelsWon": 8,
        "groundDuelsWonPercentage": 38.095238095238,
        "aerialDuelsWon": 5,
        "aerialDuelsWonPercentage": 45.454545454545,
        "totalDuelsWon": 13,
        "totalDuelsWonPercentage": 40.625,
        "minutesPlayed": 242,
        "goalConversionPercentage": 0,
        "penaltiesTaken": 0,
        "penaltyGoals": 0,
        "penaltyWon": 0,
        "penaltyConceded": 0,
        "shotFromSetPiece": 0,
        "freeKickGoal": 0,
        "goalsFromInsideTheBox": 0,
        "goalsFromOutsideTheBox": 0,
        "shotsFromInsideTheBox": 0,
        "shotsFromOutsideTheBox": 0,
        "headedGoals": 0,
        "leftFootGoals": 0,
        "rightFootGoals": 0,
        "accurateLongBalls": 1,
        "accurateLongBallsPercentage": 33.333333333333,
        "clearances": 3,
        "errorLeadToGoal": 0,
        "errorLeadToShot": 0,
        "dispossessed": 7,
        "possessionLost": 41,
        "possessionWonAttThird": 1,
        "totalChippedPasses": 9,
        "accurateChippedPasses": 4,
        "touches": 147,
        "wasFouled": 2,
        "fouls": 3,
        "hitWoodwork": 0,
        "ownGoals": 0,
        "dribbledPast": 2,
        "offsides": 0,
        "blockedShots": 1,
        "passToAssist": 0,
        "saves": 0,
        "cleanSheet": 1,
        "penaltyFaced": 0,
        "penaltySave": 0,
        "savedShotsFromInsideTheBox": 0,
        "savedShotsFromOutsideTheBox": 0,
        "goalsConcededInsideTheBox": 2,
        "goalsConcededOutsideTheBox": 0,
        "punches": 0,
        "runsOut": 0,
        "successfulRunsOut": 0,
        "highClaims": 0,
        "crossesNotClaimed": 0,
        "matchesStarted": 3,
        "penaltyConversion": 0,
        "setPieceConversion": 0,
        "totalAttemptAssist": 2,
        "totalContest": 3,
        "totalCross": 2,
        "duelLost": 19,
        "aerialLost": 6,
        "attemptPenaltyMiss": 0,
        "attemptPenaltyPost": 0,
        "attemptPenaltyTarget": 0,
        "totalLongBalls": 3,
        "goalsConceded": 2,
        "tacklesWon": 5,
        "tacklesWonPercentage": 100,
        "scoringFrequency": 0,
        "yellowRedCards": 0,
        "savesCaught": 0,
        "savesParried": 0,
        "totalOwnHalfPasses": 40,
        "totalOppositionHalfPasses": 62,
        "totwAppearances": 0,
        "id": 98822,
        "type": "overall",
        "appearances": 3,
        "statisticsType": {
            "sportSlug": "football",
            "statisticsType": "player"
        }
    }
}