{
    "meta": {
        "id": 1419346,
        "name": "Gerd Müller",
        "team": "West Germany",
        "year": "1974",
        "season_id": 17566,
        "position": "F"
    },
    "stats": {
        "rating": 7.5571428571429,
        "totalRating": 52.9,
        "countRating": 7,
        "goals": 4,
        "bigChancesCreated": 0,
        "bigChancesMissed": 0,
        "assists": 2,
        "goalsAssistsSum": 6,
        "accuratePasses": 142,
        "inaccuratePasses": 34,
        "totalPasses": 176,
        "accuratePassesPercentage": 80.681818181818,
        "accurateOwnHalfPasses": 30,
        "accurateOppositionHalfPasses": 113,
        "accurateFinalThirdPasses": 65,
        "keyPasses": 18,
        "successfulDribbles": 9,
        "successfulDribblesPercentage": 40.909090909091,
        "tackles": 7,
        "interceptions": 7,
        "yellowCards": 0,
        "directRedCards": 0,
        "redCards": 0,
        "accurateCrosses": 1,
        "accurateCrossesPercentage": 20,
        "totalShots": 29,
        "shotsOnTarget": 13,
        "shotsOffTarget": 7,
        "groundDuelsWon": 24,
        "groundDuelsWonPercentage": 42.857142857143,
        "aerialDuelsWon": 4,
        "aerialDuelsWonPercentage": 26.666666666667,
        "totalDuelsWon": 28,
        "totalDuelsWonPercentage": 39.43661971831,
        "minutesPlayed": 630,
        "goalConversionPercentage": 13.793103448276,
        "penaltiesTaken": 0,
        "penaltyGoals": 0,
        "penaltyWon": 1,
        "penaltyConceded": 0,
        "shotFromSetPiece": 0,
        "freeKickGoal": 0,
        "goalsFromInsideTheBox": 4,
        "goalsFromOutsideTheBox": 0,
        "shotsFromInsideTheBox": 28,
        "shotsFromOutsideTheBox": 1,
        "headedGoals": 1,
        "leftFootGoals": 0,
        "rightFootGoals": 3,
        "accurateLongBalls": 5,
        "accurateLongBallsPercentage": 71.428571428571,
        "clearances": 0,
        "errorLeadToGoal": 0,
        "errorLeadToShot": 0,
        "dispossessed": 7,
        "possessionLost": 59,
        "possessionWonAttThird": 1,
        "totalChippedPasses": 6,
        "accurateChippedPasses": 1,
        "touches": 280,
        "wasFouled": 8,
        "fouls": 6,
        "hitWoodwork": 2,
        "ownGoals": 0,
        "dribbledPast": 7,
        "offsides": 12,
        "blockedShots": 9,
        "passToAssist": 0,
        "saves": 0,
        "cleanSheet": 4,
        "penaltyFaced": 0,
        "penaltySave": 0,
        "savedShotsFromInsideTheBox": 0,
        "savedShotsFromOutsideTheBox": 0,
        "goalsConcededInsideTheBox": 4,
        "goalsConcededOutsideTheBox": 0,
        "punches": 0,
        "runsOut": 0,
        "successfulRunsOut": 0,
        "highClaims": 0,
        "crossesNotClaimed": 0,
        "matchesStarted": 7,
        "penaltyConversion": 0,
        "setPieceConversion": 0,
        "totalAttemptAssist": 18,
        "totalContest": 22,
        "totalCross": 5,
        "duelLost": 43,
        "aerialLost": 11,
        "attemptPenaltyMiss": 0,
        "attemptPenaltyPost": 0,
        "attemptPenaltyTarget": 0,
        "totalLongBalls": 7,
        "goalsConceded": 4,
        "tacklesWon": 5,
        "tacklesWonPercentage": 71.428571428571,
        "scoringFrequency": 157.5,
        "yellowRedCards": 0,
        "savesCaught": 0,
        "savesParried": 0,
        "totalOwnHalfPasses": 34,
        "totalOppositionHalfPasses": 147,
        "totwAppearances": 0,
        "id": 904700,
        "type": "overall",
        "appearances": 7,
        "statisticsType": {
            "sportSlug": "football",
            "statisticsType": "player"
        }
    }
}