{
    "meta": {
        "id": 1421373,
        "name": "Ciriaco Sforza",
        "team": "Switzerland",
        "year": "1994",
        "season_id": 17571,
        "position": "M"
    },
    "stats": {
        "rating": 6.95,
        "totalRating": 27.8,
        "countRating": 4,
        "goals": 0,
        "bigChancesCreated": 0,
        "bigChancesMissed": 0,
        "assists": 1,
        "goalsAssistsSum": 1,
        "accuratePasses": 138,
        "inaccuratePasses": 35,
        "totalPasses": 173,
        "accuratePassesPercentage": 79.768786127168,
        "accurateOwnHalfPasses": 49,
        "accurateOppositionHalfPasses": 91,
        "accurateFinalThirdPasses": 43,
        "keyPasses": 5,
        "successfulDribbles": 2,
        "successfulDribblesPercentage": 100,
        "tackles": 11,
        "interceptions": 13,
        "yellowCards": 0,
        "directRedCards": 0,
        "redCards": 0,
        "accurateCrosses": 2,
        "accurateCrossesPercentage": 100,
        "totalShots": 6,
        "shotsOnTarget": 3,
        "shotsOffTarget": 2,
        "groundDuelsWon": 18,
        "groundDuelsWonPercentage": 40.909090909091,
        "aerialDuelsWon": 4,
        "aerialDuelsWonPercentage": 50,
        "totalDuelsWon": 22,
        "totalDuelsWonPercentage": 42.307692307692,
        "minutesPlayed": 348,
        "goalConversionPercentage": 0,
        "penaltiesTaken": 0,
        "penaltyGoals": 0,
        "penaltyWon": 0,
        "penaltyConceded": 0,
        "shotFromSetPiece": 0,
        "freeKickGoal": 0,
        "goalsFromInsideTheBox": 0,
        "goalsFromOutsideTheBox": 0,
        "shotsFromInsideTheBox": 0,
        "shotsFromOutsideTheBox": 6,
        "headedGoals": 0,
        "leftFootGoals": 0,
        "rightFootGoals": 0,
        "accurateLongBalls": 14,
        "accurateLongBallsPercentage": 70,
        "clearances": 3,
        "errorLeadToGoal": 0,
        "errorLeadToShot": 0,
        "dispossessed": 10,
        "possessionLost": 45,
        "possessionWonAttThird": 2,
        "totalChippedPasses": 15,
        "accurateChippedPasses": 8,
        "touches": 239,
        "wasFouled": 5,
        "fouls": 10,
        "hitWoodwork": 0,
        "ownGoals": 0,
        "dribbledPast": 7,
        "offsides": 2,
        "blockedShots": 1,
        "passToAssist": 0,
        "saves": 0,
        "cleanSheet": 0,
        "penaltyFaced": 0,
        "penaltySave": 0,
        "savedShotsFromInsideTheBox": 0,
        "savedShotsFromOutsideTheBox": 0,
        "goalsConcededInsideTheBox": 4,
        "goalsConcededOutsideTheBox": 3,
        "punches": 0,
        "runsOut": 0,
        "successfulRunsOut": 0,
        "highClaims": 0,
        "crossesNotClaimed": 0,
        "matchesStarted": 4,
        "penaltyConversion": 0,
        "setPieceConversion": 0,
        "totalAttemptAssist": 5,
        "totalContest": 2,
        "totalCross": 2,
        "duelLost": 30,
        "aerialLost": 4,
        "attemptPenaltyMiss": 0,
        "attemptPenaltyPost": 0,
        "attemptPenaltyTarget": 0,
        "totalLongBalls": 20,
        "goalsConceded": 7,
        "tacklesWon": 8,
        "tacklesWonPercentage": 72.727272727273,
        "scoringFrequency": 0,
        "yellowRedCards": 0,
        "savesCaught": 0,
        "savesParried": 0,
        "totalOwnHalfPasses": 51,
        "totalOppositionHalfPasses": 124,
        "totwAppearances": 0,
        "id": 909549,
        "type": "overall",
        "appearances": 4,
        "statisticsType": {
            "sportSlug": "football",
            "statisticsType": "player"
        }
    }
}