{
    "meta": {
        "id": 1419786,
        "name": "Francesco Graziani",
        "team": "Italy",
        "year": "1982",
        "season_id": 17568,
        "position": "F"
    },
    "stats": {
        "rating": 6.8285714285714,
        "totalRating": 47.8,
        "countRating": 7,
        "goals": 1,
        "bigChancesCreated": 0,
        "bigChancesMissed": 0,
        "assists": 0,
        "goalsAssistsSum": 1,
        "accuratePasses": 108,
        "inaccuratePasses": 41,
        "totalPasses": 149,
        "accuratePassesPercentage": 72.48322147651,
        "accurateOwnHalfPasses": 30,
        "accurateOppositionHalfPasses": 81,
        "accurateFinalThirdPasses": 42,
        "keyPasses": 6,
        "successfulDribbles": 7,
        "successfulDribblesPercentage": 36.842105263158,
        "tackles": 10,
        "interceptions": 4,
        "yellowCards": 0,
        "directRedCards": 0,
        "redCards": 0,
        "accurateCrosses": 3,
        "accurateCrossesPercentage": 27.272727272727,
        "totalShots": 13,
        "shotsOnTarget": 3,
        "shotsOffTarget": 10,
        "groundDuelsWon": 31,
        "groundDuelsWonPercentage": 41.891891891892,
        "aerialDuelsWon": 7,
        "aerialDuelsWonPercentage": 43.75,
        "totalDuelsWon": 38,
        "totalDuelsWonPercentage": 42.222222222222,
        "minutesPlayed": 528,
        "goalConversionPercentage": 7.6923076923077,
        "penaltiesTaken": 0,
        "penaltyGoals": 0,
        "penaltyWon": 0,
        "penaltyConceded": 0,
        "shotFromSetPiece": 0,
        "freeKickGoal": 0,
        "goalsFromInsideTheBox": 1,
        "goalsFromOutsideTheBox": 0,
        "shotsFromInsideTheBox": 11,
        "shotsFromOutsideTheBox": 2,
        "headedGoals": 1,
        "leftFootGoals": 0,
        "rightFootGoals": 0,
        "accurateLongBalls": 1,
        "accurateLongBallsPercentage": 50,
        "clearances": 3,
        "errorLeadToGoal": 0,
        "errorLeadToShot": 0,
        "dispossessed": 14,
        "possessionLost": 77,
        "possessionWonAttThird": 0,
        "totalChippedPasses": 8,
        "accurateChippedPasses": 3,
        "touches": 254,
        "wasFouled": 14,
        "fouls": 8,
        "hitWoodwork": 0,
        "ownGoals": 0,
        "dribbledPast": 9,
        "offsides": 5,
        "blockedShots": 0,
        "passToAssist": 0,
        "saves": 0,
        "cleanSheet": 1,
        "penaltyFaced": 0,
        "penaltySave": 0,
        "savedShotsFromInsideTheBox": 0,
        "savedShotsFromOutsideTheBox": 0,
        "goalsConcededInsideTheBox": 2,
        "goalsConcededOutsideTheBox": 3,
        "punches": 0,
        "runsOut": 0,
        "successfulRunsOut": 0,
        "highClaims": 0,
        "crossesNotClaimed": 0,
        "matchesStarted": 7,
        "penaltyConversion": 0,
        "setPieceConversion": 0,
        "totalAttemptAssist": 6,
        "totalContest": 19,
        "totalCross": 11,
        "duelLost": 52,
        "aerialLost": 9,
        "attemptPenaltyMiss": 0,
        "attemptPenaltyPost": 0,
        "attemptPenaltyTarget": 0,
        "totalLongBalls": 2,
        "goalsConceded": 5,
        "tacklesWon": 5,
        "tacklesWonPercentage": 50,
        "scoringFrequency": 528,
        "yellowRedCards": 0,
        "savesCaught": 0,
        "savesParried": 0,
        "totalOwnHalfPasses": 37,
        "totalOppositionHalfPasses": 123,
        "totwAppearances": 0,
        "id": 906181,
        "type": "overall",
        "appearances": 7,
        "statisticsType": {
            "sportSlug": "football",
            "statisticsType": "player"
        }
    }
}