{
    "meta": {
        "id": 1422177,
        "name": "Ales Ceh",
        "team": "Slovenia",
        "year": "2002",
        "season_id": 2636,
        "position": "M"
    },
    "stats": {
        "rating": 6.7,
        "totalRating": 20.1,
        "countRating": 3,
        "goals": 0,
        "bigChancesCreated": 0,
        "bigChancesMissed": 0,
        "assists": 0,
        "goalsAssistsSum": 0,
        "accuratePasses": 80,
        "inaccuratePasses": 28,
        "totalPasses": 108,
        "accuratePassesPercentage": 74.074074074074,
        "accurateOwnHalfPasses": 34,
        "accurateOppositionHalfPasses": 46,
        "accurateFinalThirdPasses": 25,
        "keyPasses": 2,
        "successfulDribbles": 4,
        "successfulDribblesPercentage": 57.142857142857,
        "tackles": 13,
        "interceptions": 4,
        "yellowCards": 1,
        "directRedCards": 0,
        "redCards": 0,
        "accurateCrosses": 0,
        "accurateCrossesPercentage": 0,
        "totalShots": 0,
        "shotsOnTarget": 0,
        "shotsOffTarget": 0,
        "groundDuelsWon": 24,
        "groundDuelsWonPercentage": 54.545454545455,
        "aerialDuelsWon": 0,
        "aerialDuelsWonPercentage": 0,
        "totalDuelsWon": 24,
        "totalDuelsWonPercentage": 52.173913043478,
        "minutesPlayed": 270,
        "goalConversionPercentage": 0,
        "penaltiesTaken": 0,
        "penaltyGoals": 0,
        "penaltyWon": 0,
        "penaltyConceded": 0,
        "shotFromSetPiece": 0,
        "freeKickGoal": 0,
        "goalsFromInsideTheBox": 0,
        "goalsFromOutsideTheBox": 0,
        "shotsFromInsideTheBox": 0,
        "shotsFromOutsideTheBox": 0,
        "headedGoals": 0,
        "leftFootGoals": 0,
        "rightFootGoals": 0,
        "accurateLongBalls": 5,
        "accurateLongBallsPercentage": 41.666666666667,
        "clearances": 7,
        "errorLeadToGoal": 0,
        "errorLeadToShot": 0,
        "dispossessed": 2,
        "possessionLost": 33,
        "possessionWonAttThird": 0,
        "totalChippedPasses": 12,
        "accurateChippedPasses": 3,
        "touches": 154,
        "wasFouled": 7,
        "fouls": 10,
        "hitWoodwork": 0,
        "ownGoals": 0,
        "dribbledPast": 7,
        "offsides": 0,
        "blockedShots": 0,
        "passToAssist": 0,
        "saves": 0,
        "cleanSheet": 0,
        "penaltyFaced": 0,
        "penaltySave": 0,
        "savedShotsFromInsideTheBox": 0,
        "savedShotsFromOutsideTheBox": 0,
        "goalsConcededInsideTheBox": 6,
        "goalsConcededOutsideTheBox": 1,
        "punches": 0,
        "runsOut": 0,
        "successfulRunsOut": 0,
        "highClaims": 0,
        "crossesNotClaimed": 0,
        "matchesStarted": 3,
        "penaltyConversion": 0,
        "setPieceConversion": 0,
        "totalAttemptAssist": 2,
        "totalContest": 7,
        "totalCross": 0,
        "duelLost": 22,
        "aerialLost": 2,
        "attemptPenaltyMiss": 0,
        "attemptPenaltyPost": 0,
        "attemptPenaltyTarget": 0,
        "totalLongBalls": 12,
        "goalsConceded": 7,
        "tacklesWon": 8,
        "tacklesWonPercentage": 61.538461538462,
        "scoringFrequency": 0,
        "yellowRedCards": 0,
        "savesCaught": 0,
        "savesParried": 0,
        "totalOwnHalfPasses": 42,
        "totalOppositionHalfPasses": 66,
        "totwAppearances": 0,
        "id": 912475,
        "type": "overall",
        "appearances": 3,
        "statisticsType": {
            "sportSlug": "football",
            "statisticsType": "player"
        }
    }
}