{
    "meta": {
        "name": "Netherlands",
        "year": "1974",
        "type": "team",
        "playerCount": 15
    },
    "stats": {
        "rating": 109.1035714285713,
        "totalRating": 618.3,
        "countRating": 83,
        "goals": 15,
        "bigChancesCreated": 0,
        "bigChancesMissed": 0,
        "assists": 8,
        "goalsAssistsSum": 23,
        "accuratePasses": 2518,
        "inaccuratePasses": 475,
        "totalPasses": 2993,
        "accuratePassesPercentage": 1212.26613444276,
        "accurateOwnHalfPasses": 974,
        "accurateOppositionHalfPasses": 1616,
        "accurateFinalThirdPasses": 871,
        "keyPasses": 104,
        "successfulDribbles": 100,
        "successfulDribblesPercentage": 646.389516280821,
        "tackles": 173,
        "interceptions": 173,
        "yellowCards": 11,
        "directRedCards": 0,
        "redCards": 0,
        "accurateCrosses": 72,
        "accurateCrossesPercentage": 340.57721869235405,
        "totalShots": 137,
        "shotsOnTarget": 52,
        "shotsOffTarget": 67,
        "groundDuelsWon": 403,
        "groundDuelsWonPercentage": 572.139703374179,
        "aerialDuelsWon": 45,
        "aerialDuelsWonPercentage": 685.010683760685,
        "totalDuelsWon": 448,
        "totalDuelsWonPercentage": 626.0318558147901,
        "minutesPlayed": 6930,
        "goalConversionPercentage": 105.1761963526658,
        "penaltiesTaken": 3,
        "penaltyGoals": 3,
        "penaltyWon": 3,
        "penaltyConceded": 1,
        "shotFromSetPiece": 8,
        "freeKickGoal": 0,
        "goalsFromInsideTheBox": 14,
        "goalsFromOutsideTheBox": 1,
        "shotsFromInsideTheBox": 78,
        "shotsFromOutsideTheBox": 59,
        "headedGoals": 3,
        "leftFootGoals": 2,
        "rightFootGoals": 10,
        "accurateLongBalls": 216,
        "accurateLongBallsPercentage": 953.726305043372,
        "clearances": 137,
        "errorLeadToGoal": 0,
        "errorLeadToShot": 0,
        "dispossessed": 53,
        "possessionLost": 822,
        "possessionWonAttThird": 38,
        "totalChippedPasses": 290,
        "accurateChippedPasses": 167,
        "touches": 4590,
        "wasFouled": 130,
        "fouls": 178,
        "hitWoodwork": 3,
        "ownGoals": 1,
        "dribbledPast": 84,
        "offsides": 35,
        "blockedShots": 18,
        "passToAssist": 0,
        "saves": 12,
        "cleanSheet": 51,
        "penaltyFaced": 1,
        "penaltySave": 0,
        "savedShotsFromInsideTheBox": 7,
        "savedShotsFromOutsideTheBox": 5,
        "goalsConcededInsideTheBox": 33,
        "goalsConcededOutsideTheBox": 0,
        "punches": 14,
        "runsOut": 11,
        "successfulRunsOut": 10,
        "highClaims": 4,
        "crossesNotClaimed": 1,
        "matchesStarted": 77,
        "penaltyConversion": 100,
        "setPieceConversion": 0,
        "totalAttemptAssist": 104,
        "totalContest": 182,
        "totalCross": 241,
        "duelLost": 431,
        "aerialLost": 41,
        "attemptPenaltyMiss": 0,
        "attemptPenaltyPost": 0,
        "attemptPenaltyTarget": 0,
        "totalLongBalls": 324,
        "goalsConceded": 33,
        "tacklesWon": 133,
        "tacklesWonPercentage": 914.9327865117339,
        "scoringFrequency": 1664.3,
        "yellowRedCards": 0,
        "savesCaught": 4,
        "savesParried": 5,
        "totalOwnHalfPasses": 1033,
        "totalOppositionHalfPasses": 2201,
        "totwAppearances": 0,
        "id": 13577934,
        "appearances": 85,
        "averageRating": 7.27357142857142
    }
}