{
    "meta": {
        "name": "Belgium",
        "year": "2018",
        "type": "team",
        "playerCount": 21
    },
    "stats": {
        "rating": 147.6083333333333,
        "totalRating": 660.4,
        "countRating": 93,
        "goals": 15,
        "bigChancesCreated": 18,
        "bigChancesMissed": 13,
        "assists": 12,
        "goalsAssistsSum": 27,
        "accuratePasses": 3114,
        "inaccuratePasses": 494,
        "totalPasses": 3608,
        "accuratePassesPercentage": 1790.888171375712,
        "accurateOwnHalfPasses": 1613,
        "accurateOppositionHalfPasses": 1533,
        "accurateFinalThirdPasses": 657,
        "keyPasses": 88,
        "successfulDribbles": 94,
        "successfulDribblesPercentage": 1105.732600732601,
        "tackles": 93,
        "interceptions": 53,
        "yellowCards": 11,
        "directRedCards": 0,
        "redCards": 0,
        "accurateCrosses": 32,
        "accurateCrossesPercentage": 591.8151260504201,
        "totalShots": 106,
        "shotsOnTarget": 40,
        "shotsOffTarget": 39,
        "groundDuelsWon": 260,
        "groundDuelsWonPercentage": 941.9822093310611,
        "aerialDuelsWon": 97,
        "aerialDuelsWonPercentage": 1099.4369994194672,
        "totalDuelsWon": 357,
        "totalDuelsWonPercentage": 1061.3343580635042,
        "minutesPlayed": 7139,
        "goalConversionPercentage": 227.8943115707817,
        "penaltiesTaken": 1,
        "penaltyGoals": 1,
        "penaltyWon": 1,
        "penaltyConceded": 0,
        "shotFromSetPiece": 4,
        "freeKickGoal": 0,
        "goalsFromInsideTheBox": 14,
        "goalsFromOutsideTheBox": 1,
        "shotsFromInsideTheBox": 10,
        "shotsFromOutsideTheBox": 2,
        "headedGoals": 3,
        "leftFootGoals": 6,
        "rightFootGoals": 6,
        "accurateLongBalls": 174,
        "accurateLongBallsPercentage": 1252.848302441545,
        "clearances": 118,
        "errorLeadToGoal": 1,
        "errorLeadToShot": 1,
        "dispossessed": 68,
        "possessionLost": 793,
        "possessionWonAttThird": 33,
        "totalChippedPasses": 192,
        "accurateChippedPasses": 96,
        "touches": 4817,
        "wasFouled": 74,
        "fouls": 99,
        "hitWoodwork": 2,
        "ownGoals": 0,
        "dribbledPast": 68,
        "offsides": 8,
        "blockedShots": 27,
        "passToAssist": 2,
        "saves": 27,
        "cleanSheet": 25,
        "penaltyFaced": 0,
        "penaltySave": 0,
        "savedShotsFromInsideTheBox": 11,
        "savedShotsFromOutsideTheBox": 14,
        "goalsConcededInsideTheBox": 55,
        "goalsConcededOutsideTheBox": 11,
        "punches": 1,
        "runsOut": 4,
        "successfulRunsOut": 4,
        "highClaims": 6,
        "crossesNotClaimed": 0,
        "matchesStarted": 77,
        "penaltyConversion": 100,
        "setPieceConversion": 0,
        "totalAttemptAssist": 86,
        "totalContest": 122,
        "totalCross": 103,
        "duelLost": 340,
        "aerialLost": 86,
        "attemptPenaltyMiss": 0,
        "attemptPenaltyPost": 0,
        "attemptPenaltyTarget": 0,
        "totalLongBalls": 327,
        "goalsConceded": 66,
        "tacklesWon": 63,
        "tacklesWonPercentage": 1198.214285714286,
        "scoringFrequency": 3053.25,
        "yellowRedCards": 0,
        "savesCaught": 0,
        "savesParried": 8,
        "totalOwnHalfPasses": 1719,
        "totalOppositionHalfPasses": 1992,
        "totwAppearances": 8,
        "id": 2342223,
        "appearances": 95,
        "averageRating": 7.028968253968252
    }
}