{
    "meta": {
        "id": 1196,
        "name": "Ricardo Carvalho",
        "team": "Portugal",
        "year": "2006",
        "season_id": 16,
        "position": "D"
    },
    "stats": {
        "rating": 7.35,
        "totalRating": 44.1,
        "countRating": 6,
        "goals": 0,
        "bigChancesCreated": 0,
        "bigChancesMissed": 0,
        "assists": 0,
        "goalsAssistsSum": 0,
        "accuratePasses": 195,
        "inaccuratePasses": 39,
        "totalPasses": 234,
        "accuratePassesPercentage": 83.333333333333,
        "accurateOwnHalfPasses": 135,
        "accurateOppositionHalfPasses": 60,
        "accurateFinalThirdPasses": 16,
        "keyPasses": 2,
        "successfulDribbles": 0,
        "successfulDribblesPercentage": 0,
        "tackles": 16,
        "interceptions": 17,
        "yellowCards": 2,
        "directRedCards": 0,
        "redCards": 0,
        "accurateCrosses": 0,
        "accurateCrossesPercentage": 0,
        "totalShots": 2,
        "shotsOnTarget": 0,
        "shotsOffTarget": 2,
        "groundDuelsWon": 20,
        "groundDuelsWonPercentage": 62.5,
        "aerialDuelsWon": 7,
        "aerialDuelsWonPercentage": 53.846153846154,
        "totalDuelsWon": 27,
        "totalDuelsWonPercentage": 60,
        "minutesPlayed": 570,
        "goalConversionPercentage": 0,
        "penaltiesTaken": 0,
        "penaltyGoals": 0,
        "penaltyWon": 0,
        "penaltyConceded": 1,
        "shotFromSetPiece": 0,
        "freeKickGoal": 0,
        "goalsFromInsideTheBox": 0,
        "goalsFromOutsideTheBox": 0,
        "shotsFromInsideTheBox": 1,
        "shotsFromOutsideTheBox": 1,
        "headedGoals": 0,
        "leftFootGoals": 0,
        "rightFootGoals": 0,
        "accurateLongBalls": 23,
        "accurateLongBallsPercentage": 54.761904761905,
        "clearances": 34,
        "errorLeadToGoal": 0,
        "errorLeadToShot": 0,
        "dispossessed": 1,
        "possessionLost": 44,
        "possessionWonAttThird": 0,
        "totalChippedPasses": 10,
        "accurateChippedPasses": 6,
        "touches": 321,
        "wasFouled": 4,
        "fouls": 7,
        "hitWoodwork": 0,
        "ownGoals": 0,
        "dribbledPast": 3,
        "offsides": 0,
        "blockedShots": 0,
        "passToAssist": 0,
        "saves": 0,
        "cleanSheet": 4,
        "penaltyFaced": 0,
        "penaltySave": 0,
        "savedShotsFromInsideTheBox": 0,
        "savedShotsFromOutsideTheBox": 0,
        "goalsConcededInsideTheBox": 2,
        "goalsConcededOutsideTheBox": 0,
        "punches": 0,
        "runsOut": 0,
        "successfulRunsOut": 0,
        "highClaims": 0,
        "crossesNotClaimed": 0,
        "matchesStarted": 6,
        "penaltyConversion": 0,
        "setPieceConversion": 0,
        "totalAttemptAssist": 2,
        "totalContest": 1,
        "totalCross": 1,
        "duelLost": 18,
        "aerialLost": 6,
        "attemptPenaltyMiss": 0,
        "attemptPenaltyPost": 0,
        "attemptPenaltyTarget": 0,
        "totalLongBalls": 42,
        "goalsConceded": 2,
        "tacklesWon": 10,
        "tacklesWonPercentage": 62.5,
        "scoringFrequency": 0,
        "yellowRedCards": 0,
        "savesCaught": 0,
        "savesParried": 0,
        "totalOwnHalfPasses": 150,
        "totalOppositionHalfPasses": 85,
        "totwAppearances": 0,
        "id": 913875,
        "type": "overall",
        "appearances": 6,
        "statisticsType": {
            "sportSlug": "football",
            "statisticsType": "player"
        }
    }
}