{
    "meta": {
        "id": 1421486,
        "name": "Ronald de Boer",
        "team": "Netherlands",
        "year": "1998",
        "season_id": 1151,
        "position": "M"
    },
    "stats": {
        "rating": 7.4833333333333,
        "totalRating": 44.9,
        "countRating": 6,
        "goals": 2,
        "bigChancesCreated": 0,
        "bigChancesMissed": 0,
        "assists": 2,
        "goalsAssistsSum": 4,
        "accuratePasses": 265,
        "inaccuratePasses": 55,
        "totalPasses": 320,
        "accuratePassesPercentage": 82.8125,
        "accurateOwnHalfPasses": 59,
        "accurateOppositionHalfPasses": 214,
        "accurateFinalThirdPasses": 120,
        "keyPasses": 20,
        "successfulDribbles": 18,
        "successfulDribblesPercentage": 62.068965517241,
        "tackles": 12,
        "interceptions": 6,
        "yellowCards": 0,
        "directRedCards": 0,
        "redCards": 0,
        "accurateCrosses": 8,
        "accurateCrossesPercentage": 24.242424242424,
        "totalShots": 7,
        "shotsOnTarget": 4,
        "shotsOffTarget": 2,
        "groundDuelsWon": 40,
        "groundDuelsWonPercentage": 54.054054054054,
        "aerialDuelsWon": 6,
        "aerialDuelsWonPercentage": 50,
        "totalDuelsWon": 46,
        "totalDuelsWonPercentage": 53.488372093023,
        "minutesPlayed": 527,
        "goalConversionPercentage": 28.571428571429,
        "penaltiesTaken": 0,
        "penaltyGoals": 0,
        "penaltyWon": 0,
        "penaltyConceded": 0,
        "shotFromSetPiece": 0,
        "freeKickGoal": 0,
        "goalsFromInsideTheBox": 2,
        "goalsFromOutsideTheBox": 0,
        "shotsFromInsideTheBox": 4,
        "shotsFromOutsideTheBox": 3,
        "headedGoals": 0,
        "leftFootGoals": 0,
        "rightFootGoals": 2,
        "accurateLongBalls": 22,
        "accurateLongBallsPercentage": 66.666666666667,
        "clearances": 6,
        "errorLeadToGoal": 0,
        "errorLeadToShot": 0,
        "dispossessed": 9,
        "possessionLost": 105,
        "possessionWonAttThird": 0,
        "totalChippedPasses": 25,
        "accurateChippedPasses": 15,
        "touches": 467,
        "wasFouled": 10,
        "fouls": 6,
        "hitWoodwork": 0,
        "ownGoals": 0,
        "dribbledPast": 9,
        "offsides": 1,
        "blockedShots": 1,
        "passToAssist": 0,
        "saves": 0,
        "cleanSheet": 0,
        "penaltyFaced": 0,
        "penaltySave": 0,
        "savedShotsFromInsideTheBox": 0,
        "savedShotsFromOutsideTheBox": 0,
        "goalsConcededInsideTheBox": 5,
        "goalsConcededOutsideTheBox": 0,
        "punches": 0,
        "runsOut": 0,
        "successfulRunsOut": 0,
        "highClaims": 0,
        "crossesNotClaimed": 0,
        "matchesStarted": 6,
        "penaltyConversion": 0,
        "setPieceConversion": 0,
        "totalAttemptAssist": 20,
        "totalContest": 29,
        "totalCross": 33,
        "duelLost": 40,
        "aerialLost": 6,
        "attemptPenaltyMiss": 0,
        "attemptPenaltyPost": 0,
        "attemptPenaltyTarget": 0,
        "totalLongBalls": 33,
        "goalsConceded": 5,
        "tacklesWon": 10,
        "tacklesWonPercentage": 83.333333333333,
        "scoringFrequency": 263.5,
        "yellowRedCards": 0,
        "savesCaught": 0,
        "savesParried": 0,
        "totalOwnHalfPasses": 71,
        "totalOppositionHalfPasses": 282,
        "totwAppearances": 0,
        "goalKicks": 0,
        "ballRecovery": 21,
        "id": 911020,
        "type": "overall",
        "appearances": 6,
        "statisticsType": {
            "sportSlug": "football",
            "statisticsType": "player"
        }
    }
}