{
    "meta": {
        "id": 124712,
        "name": "Neymar",
        "team": "Brazil",
        "year": "2022",
        "season_id": 41087,
        "position": "F"
    },
    "stats": {
        "rating": 6.8666666666667,
        "totalRating": 20.6,
        "countRating": 3,
        "goals": 2,
        "bigChancesCreated": 1,
        "bigChancesMissed": 3,
        "assists": 1,
        "expectedAssists": 0.5216976,
        "goalsAssistsSum": 3,
        "accuratePasses": 115,
        "inaccuratePasses": 27,
        "totalPasses": 142,
        "accuratePassesPercentage": 80.985915492958,
        "accurateOwnHalfPasses": 23,
        "accurateOppositionHalfPasses": 96,
        "accurateFinalThirdPasses": 52,
        "keyPasses": 6,
        "successfulDribbles": 6,
        "successfulDribblesPercentage": 31.578947368421,
        "tackles": 1,
        "interceptions": 1,
        "yellowCards": 0,
        "directRedCards": 0,
        "redCards": 0,
        "accurateCrosses": 4,
        "accurateCrossesPercentage": 50,
        "totalShots": 12,
        "shotsOnTarget": 7,
        "shotsOffTarget": 3,
        "groundDuelsWon": 23,
        "groundDuelsWonPercentage": 44.230769230769,
        "aerialDuelsWon": 0,
        "aerialDuelsWonPercentage": 0,
        "totalDuelsWon": 23,
        "totalDuelsWonPercentage": 41.818181818182,
        "minutesPlayed": 281,
        "goalConversionPercentage": 16.666666666667,
        "penaltiesTaken": 1,
        "penaltyGoals": 1,
        "penaltyWon": 0,
        "penaltyConceded": 0,
        "shotFromSetPiece": 3,
        "freeKickGoal": 0,
        "goalsFromInsideTheBox": 2,
        "goalsFromOutsideTheBox": 0,
        "shotsFromInsideTheBox": 8,
        "shotsFromOutsideTheBox": 4,
        "headedGoals": 0,
        "leftFootGoals": 0,
        "rightFootGoals": 2,
        "accurateLongBalls": 2,
        "accurateLongBallsPercentage": 66.666666666667,
        "clearances": 0,
        "errorLeadToGoal": 0,
        "errorLeadToShot": 0,
        "dispossessed": 12,
        "possessionLost": 67,
        "possessionWonAttThird": 1,
        "totalChippedPasses": 7,
        "accurateChippedPasses": 2,
        "touches": 240,
        "wasFouled": 16,
        "fouls": 4,
        "hitWoodwork": 0,
        "ownGoals": 0,
        "dribbledPast": 0,
        "offsides": 2,
        "blockedShots": 2,
        "passToAssist": 0,
        "saves": 0,
        "cleanSheet": 0,
        "penaltyFaced": 0,
        "penaltySave": 0,
        "savedShotsFromInsideTheBox": 0,
        "savedShotsFromOutsideTheBox": 0,
        "goalsConcededInsideTheBox": 1,
        "goalsConcededOutsideTheBox": 1,
        "punches": 0,
        "runsOut": 0,
        "successfulRunsOut": 0,
        "highClaims": 0,
        "crossesNotClaimed": 0,
        "matchesStarted": 3,
        "penaltyConversion": 100,
        "setPieceConversion": 0,
        "totalAttemptAssist": 6,
        "totalContest": 19,
        "totalCross": 8,
        "duelLost": 32,
        "aerialLost": 3,
        "attemptPenaltyMiss": 0,
        "attemptPenaltyPost": 0,
        "attemptPenaltyTarget": 0,
        "totalLongBalls": 3,
        "goalsConceded": 2,
        "tacklesWon": 0,
        "tacklesWonPercentage": 0,
        "scoringFrequency": 140.5,
        "yellowRedCards": 0,
        "savesCaught": 0,
        "savesParried": 0,
        "totalOwnHalfPasses": 25,
        "totalOppositionHalfPasses": 125,
        "totwAppearances": 0,
        "expectedGoals": 2.7161,
        "id": 924787,
        "type": "overall",
        "appearances": 3,
        "statisticsType": {
            "sportSlug": "football",
            "statisticsType": "player"
        }
    }
}