{
    "meta": {
        "id": 4735,
        "name": "Zinedine Zidane",
        "team": "France",
        "year": "1998",
        "season_id": 1151,
        "position": "M"
    },
    "stats": {
        "rating": 8,
        "totalRating": 40,
        "countRating": 5,
        "goals": 2,
        "bigChancesCreated": 0,
        "bigChancesMissed": 0,
        "assists": 1,
        "goalsAssistsSum": 3,
        "accuratePasses": 225,
        "inaccuratePasses": 55,
        "totalPasses": 280,
        "accuratePassesPercentage": 80.357142857143,
        "accurateOwnHalfPasses": 58,
        "accurateOppositionHalfPasses": 174,
        "accurateFinalThirdPasses": 91,
        "keyPasses": 18,
        "successfulDribbles": 10,
        "successfulDribblesPercentage": 43.478260869565,
        "tackles": 7,
        "interceptions": 5,
        "yellowCards": 1,
        "directRedCards": 1,
        "redCards": 1,
        "accurateCrosses": 7,
        "accurateCrossesPercentage": 26.923076923077,
        "totalShots": 22,
        "shotsOnTarget": 6,
        "shotsOffTarget": 10,
        "groundDuelsWon": 27,
        "groundDuelsWonPercentage": 44.262295081967,
        "aerialDuelsWon": 4,
        "aerialDuelsWonPercentage": 80,
        "totalDuelsWon": 31,
        "totalDuelsWonPercentage": 46.969696969697,
        "minutesPlayed": 460,
        "goalConversionPercentage": 9.0909090909091,
        "penaltiesTaken": 0,
        "penaltyGoals": 0,
        "penaltyWon": 0,
        "penaltyConceded": 0,
        "shotFromSetPiece": 3,
        "freeKickGoal": 0,
        "goalsFromInsideTheBox": 2,
        "goalsFromOutsideTheBox": 0,
        "shotsFromInsideTheBox": 11,
        "shotsFromOutsideTheBox": 11,
        "headedGoals": 2,
        "leftFootGoals": 0,
        "rightFootGoals": 0,
        "accurateLongBalls": 23,
        "accurateLongBallsPercentage": 76.666666666667,
        "clearances": 2,
        "errorLeadToGoal": 0,
        "errorLeadToShot": 0,
        "dispossessed": 8,
        "possessionLost": 101,
        "possessionWonAttThird": 3,
        "totalChippedPasses": 30,
        "accurateChippedPasses": 20,
        "touches": 418,
        "wasFouled": 10,
        "fouls": 9,
        "hitWoodwork": 0,
        "ownGoals": 0,
        "dribbledPast": 4,
        "offsides": 1,
        "blockedShots": 6,
        "passToAssist": 0,
        "saves": 0,
        "cleanSheet": 3,
        "penaltyFaced": 0,
        "penaltySave": 0,
        "savedShotsFromInsideTheBox": 0,
        "savedShotsFromOutsideTheBox": 0,
        "goalsConcededInsideTheBox": 1,
        "goalsConcededOutsideTheBox": 0,
        "punches": 0,
        "runsOut": 0,
        "successfulRunsOut": 0,
        "highClaims": 0,
        "crossesNotClaimed": 0,
        "matchesStarted": 5,
        "penaltyConversion": 0,
        "setPieceConversion": 0,
        "totalAttemptAssist": 18,
        "totalContest": 23,
        "totalCross": 26,
        "duelLost": 35,
        "aerialLost": 1,
        "attemptPenaltyMiss": 0,
        "attemptPenaltyPost": 0,
        "attemptPenaltyTarget": 0,
        "totalLongBalls": 30,
        "goalsConceded": 1,
        "tacklesWon": 5,
        "tacklesWonPercentage": 71.428571428571,
        "scoringFrequency": 230,
        "yellowRedCards": 0,
        "savesCaught": 0,
        "savesParried": 0,
        "totalOwnHalfPasses": 63,
        "totalOppositionHalfPasses": 243,
        "totwAppearances": 0,
        "goalKicks": 0,
        "ballRecovery": 37,
        "id": 910686,
        "type": "overall",
        "appearances": 5,
        "statisticsType": {
            "sportSlug": "football",
            "statisticsType": "player"
        }
    }
}