{
    "meta": {
        "id": 1422476,
        "name": "David Rozehnal",
        "team": "Czechia",
        "year": "2006",
        "season_id": 16,
        "position": "D"
    },
    "stats": {
        "rating": 7.1,
        "totalRating": 21.3,
        "countRating": 3,
        "goals": 0,
        "bigChancesCreated": 0,
        "bigChancesMissed": 0,
        "assists": 0,
        "goalsAssistsSum": 0,
        "accuratePasses": 83,
        "inaccuratePasses": 22,
        "totalPasses": 105,
        "accuratePassesPercentage": 79.047619047619,
        "accurateOwnHalfPasses": 52,
        "accurateOppositionHalfPasses": 32,
        "accurateFinalThirdPasses": 11,
        "keyPasses": 1,
        "successfulDribbles": 0,
        "successfulDribblesPercentage": 0,
        "tackles": 4,
        "interceptions": 11,
        "yellowCards": 1,
        "directRedCards": 0,
        "redCards": 0,
        "accurateCrosses": 1,
        "accurateCrossesPercentage": 100,
        "totalShots": 0,
        "shotsOnTarget": 0,
        "shotsOffTarget": 0,
        "groundDuelsWon": 8,
        "groundDuelsWonPercentage": 61.538461538462,
        "aerialDuelsWon": 5,
        "aerialDuelsWonPercentage": 45.454545454545,
        "totalDuelsWon": 13,
        "totalDuelsWonPercentage": 54.166666666667,
        "minutesPlayed": 270,
        "goalConversionPercentage": 0,
        "penaltiesTaken": 0,
        "penaltyGoals": 0,
        "penaltyWon": 0,
        "penaltyConceded": 0,
        "shotFromSetPiece": 0,
        "freeKickGoal": 0,
        "goalsFromInsideTheBox": 0,
        "goalsFromOutsideTheBox": 0,
        "shotsFromInsideTheBox": 0,
        "shotsFromOutsideTheBox": 0,
        "headedGoals": 0,
        "leftFootGoals": 0,
        "rightFootGoals": 0,
        "accurateLongBalls": 13,
        "accurateLongBallsPercentage": 54.166666666667,
        "clearances": 22,
        "errorLeadToGoal": 0,
        "errorLeadToShot": 0,
        "dispossessed": 0,
        "possessionLost": 26,
        "possessionWonAttThird": 0,
        "totalChippedPasses": 11,
        "accurateChippedPasses": 8,
        "touches": 155,
        "wasFouled": 4,
        "fouls": 4,
        "hitWoodwork": 0,
        "ownGoals": 0,
        "dribbledPast": 1,
        "offsides": 0,
        "blockedShots": 0,
        "passToAssist": 0,
        "saves": 0,
        "cleanSheet": 1,
        "penaltyFaced": 0,
        "penaltySave": 0,
        "savedShotsFromInsideTheBox": 0,
        "savedShotsFromOutsideTheBox": 0,
        "goalsConcededInsideTheBox": 4,
        "goalsConcededOutsideTheBox": 0,
        "punches": 0,
        "runsOut": 0,
        "successfulRunsOut": 0,
        "highClaims": 0,
        "crossesNotClaimed": 0,
        "matchesStarted": 3,
        "penaltyConversion": 0,
        "setPieceConversion": 0,
        "totalAttemptAssist": 1,
        "totalContest": 0,
        "totalCross": 1,
        "duelLost": 11,
        "aerialLost": 6,
        "attemptPenaltyMiss": 0,
        "attemptPenaltyPost": 0,
        "attemptPenaltyTarget": 0,
        "totalLongBalls": 24,
        "goalsConceded": 4,
        "tacklesWon": 4,
        "tacklesWonPercentage": 100,
        "scoringFrequency": 0,
        "yellowRedCards": 0,
        "savesCaught": 0,
        "savesParried": 0,
        "totalOwnHalfPasses": 57,
        "totalOppositionHalfPasses": 49,
        "totwAppearances": 0,
        "id": 914378,
        "type": "overall",
        "appearances": 3,
        "statisticsType": {
            "sportSlug": "football",
            "statisticsType": "player"
        }
    }
}