{
    "meta": {
        "id": 1418959,
        "name": "Uwe Seeler",
        "team": "West Germany",
        "year": "1970",
        "season_id": 17565,
        "position": "F"
    },
    "stats": {
        "rating": 7.8166666666667,
        "totalRating": 46.9,
        "countRating": 6,
        "goals": 3,
        "bigChancesCreated": 0,
        "bigChancesMissed": 0,
        "assists": 3,
        "goalsAssistsSum": 6,
        "accuratePasses": 170,
        "inaccuratePasses": 41,
        "totalPasses": 211,
        "accuratePassesPercentage": 80.568720379147,
        "accurateOwnHalfPasses": 76,
        "accurateOppositionHalfPasses": 96,
        "accurateFinalThirdPasses": 46,
        "keyPasses": 8,
        "successfulDribbles": 3,
        "successfulDribblesPercentage": 60,
        "tackles": 12,
        "interceptions": 10,
        "yellowCards": 0,
        "directRedCards": 0,
        "redCards": 0,
        "accurateCrosses": 2,
        "accurateCrossesPercentage": 28.571428571429,
        "totalShots": 29,
        "shotsOnTarget": 9,
        "shotsOffTarget": 15,
        "groundDuelsWon": 26,
        "groundDuelsWonPercentage": 54.166666666667,
        "aerialDuelsWon": 16,
        "aerialDuelsWonPercentage": 59.259259259259,
        "totalDuelsWon": 42,
        "totalDuelsWonPercentage": 56,
        "minutesPlayed": 600,
        "goalConversionPercentage": 10.344827586207,
        "penaltiesTaken": 0,
        "penaltyGoals": 0,
        "penaltyWon": 0,
        "penaltyConceded": 0,
        "shotFromSetPiece": 0,
        "freeKickGoal": 0,
        "goalsFromInsideTheBox": 3,
        "goalsFromOutsideTheBox": 0,
        "shotsFromInsideTheBox": 24,
        "shotsFromOutsideTheBox": 5,
        "headedGoals": 1,
        "leftFootGoals": 0,
        "rightFootGoals": 2,
        "accurateLongBalls": 6,
        "accurateLongBallsPercentage": 85.714285714286,
        "clearances": 6,
        "errorLeadToGoal": 0,
        "errorLeadToShot": 0,
        "dispossessed": 12,
        "possessionLost": 61,
        "possessionWonAttThird": 1,
        "totalChippedPasses": 6,
        "accurateChippedPasses": 3,
        "touches": 323,
        "wasFouled": 11,
        "fouls": 8,
        "hitWoodwork": 1,
        "ownGoals": 0,
        "dribbledPast": 1,
        "offsides": 3,
        "blockedShots": 5,
        "passToAssist": 0,
        "saves": 0,
        "cleanSheet": 1,
        "penaltyFaced": 0,
        "penaltySave": 0,
        "savedShotsFromInsideTheBox": 0,
        "savedShotsFromOutsideTheBox": 0,
        "goalsConcededInsideTheBox": 6,
        "goalsConcededOutsideTheBox": 4,
        "punches": 0,
        "runsOut": 0,
        "successfulRunsOut": 0,
        "highClaims": 0,
        "crossesNotClaimed": 0,
        "matchesStarted": 6,
        "penaltyConversion": 0,
        "setPieceConversion": 0,
        "totalAttemptAssist": 8,
        "totalContest": 5,
        "totalCross": 7,
        "duelLost": 33,
        "aerialLost": 11,
        "attemptPenaltyMiss": 0,
        "attemptPenaltyPost": 0,
        "attemptPenaltyTarget": 0,
        "totalLongBalls": 7,
        "goalsConceded": 10,
        "tacklesWon": 8,
        "tacklesWonPercentage": 66.666666666667,
        "scoringFrequency": 200,
        "yellowRedCards": 0,
        "savesCaught": 0,
        "savesParried": 0,
        "totalOwnHalfPasses": 83,
        "totalOppositionHalfPasses": 135,
        "totwAppearances": 0,
        "id": 904339,
        "type": "overall",
        "appearances": 6,
        "statisticsType": {
            "sportSlug": "football",
            "statisticsType": "player"
        }
    }
}